Metadata-Version: 1.1
Name: tdapi
Version: 2.0.17
Summary: Python UIAutomation for Windows
Home-page: https://github.com/yinkaisheng/Python-UIAutomation-for-Windows
Author: yinkaisheng
Author-email: yinkaisheng@foxmail.com
License: Apache 2.0
Keywords: windows ui automation uiautomation inspect
Platform: Windows Only
Classifier: Programming Language :: Python :: 3.4
Classifier: Programming Language :: Python :: 3.5
Classifier: Programming Language :: Python :: 3.6
Classifier: Programming Language :: Python :: 3.7
Classifier: Programming Language :: Python :: 3.8
